DP/__about__.py
DP/__init__.py
DP/__pycache__/__about__.cpython-38.pyc
DP/__pycache__/__init__.cpython-38.pyc
DP/problems/_Best_Time_to_Buy_and_Sell_Stock.py
DP/problems/_Coin_Change.py
DP/problems/_Decode_Ways.py
DP/problems/_Fibonacci_Numbers.py
DP/problems/_House_Robber.py
DP/problems/_Maximum_Subarray.py
DP/problems/_Min_Cost_Climbing_Stairs.py
DP/problems/_Word_Break.py
DP/problems/__init__.py
DP/problems/__pycache__/_Best_Time_to_Buy_and_Sell_Stock.cpython-38.pyc
DP/problems/__pycache__/_Coin_Change.cpython-38.pyc
DP/problems/__pycache__/_Decode_Ways.cpython-38.pyc
DP/problems/__pycache__/_Fibonacci_Numbers.cpython-38.pyc
DP/problems/__pycache__/_House_Robber.cpython-38.pyc
DP/problems/__pycache__/_Maximum_Subarray.cpython-38.pyc
DP/problems/__pycache__/_Min_Cost_Climbing_Stairs.cpython-38.pyc
DP/problems/__pycache__/_Word_Break.cpython-38.pyc
DP/problems/__pycache__/__init__.cpython-38.pyc
dynamic_programming-0.0.2.dist-info/LICENSE
dynamic_programming-0.0.2.dist-info/METADATA
dynamic_programming-0.0.2.dist-info/WHEEL
dynamic_programming-0.0.2.dist-info/top_level.txt
dynamic_programming-0.0.2.dist-info/RECORD
