Metadata-Version: 2.1
Name: dynamic-programming
Version: 0.0.2
Summary: Library for Studying Dynamic Programming
Home-page: https://github.com/daniel-yj-yang/dynamic-programming
Author: Daniel Yang
Author-email: daniel.yj.yang@gmail.com
License: BSD-3-Clause License
Platform: UNKNOWN
Classifier: Development Status :: 3 - Alpha
Classifier: Programming Language :: Python :: 3
Classifier: Programming Language :: Python :: 3.8
Classifier: Programming Language :: Python :: 3.9
Classifier: License :: OSI Approved :: BSD License
Classifier: Operating System :: OS Independent
Requires-Python: >=3.8
License-File: LICENSE
Requires-Dist: treekit (>=0.0.21)
